Authify/__init__.py
Authify/client.py
Authify-0.0.4.dist-info/METADATA
Authify-0.0.4.dist-info/WHEEL
Authify-0.0.4.dist-info/top_level.txt
Authify-0.0.4.dist-info/RECORD
