Metadata-Version: 2.1
Name: Authify
Version: 0.0.4
Summary: Package for the Authify.biz API
Author: Clynt
Author-email: <mail@clynt.me>
License: UNKNOWN
Keywords: wrapper,apiwrapper,authify,auth,authsystem
Platform: UNKNOWN
Classifier: Development Status :: 1 - Planning
Classifier: Intended Audience :: Developers
Classifier: Programming Language :: Python :: 3
Classifier: Operating System :: Unix
Classifier: Operating System :: MacOS :: MacOS X
Classifier: Operating System :: Microsoft :: Windows
Requires-Dist: requests
Requires-Dist: pycryptodome
Requires-Dist: fingerprint
